<?xml version="1.0" encoding="UTF-8" ?>
<data game="game">
  <antcolor>red</antcolor>
  <author>Jiyun</author>
  <description>Generic Template</description>
  <emptycolor>purple</emptycolor>
  <foodcolor>silver</foodcolor>
  <model>foragingants</model>
  <movebias>0.96</movebias>
  <nestcolor>green</nestcolor>
  <numCols>70</numCols>
  <numRows>70</numRows>
  <numberofants>100</numberofants>
  <numberofsides>4</numberofsides>
  <phermoneamount>100</phermoneamount>
  <phermonecolor>blue</phermonecolor>
  <radius>2</radius>
  <shape>square</shape>
  <shapeCoords>10,10,15,60,60,60</shapeCoords>
  <template>generic</template>
  <title>Foraging Ants</title>
  <weakphermonecolor>skyblue</weakphermonecolor>
</data>