<?xml version="1.0" encoding="UTF-8" ?>
<data game="game">
  <author>Jiyun</author>
  <blockcolor>black</blockcolor>
  <blockratio>0.6</blockratio>
  <description>Attempted to simulate water flowing to create new waterways (e.g. river).
  </description>
  <emptycolor>lightgrey</emptycolor>
  <model>percolation</model>
  <numCols>50</numCols>
  <numRows>50</numRows>
  <numberofsides>3</numberofsides>
  <randomseed>100</randomseed>
  <shape>triangle</shape>
  <template>random_one</template>
  <title>Percolation</title>
  <watercolor>blue</watercolor>
  <watertoemptyratio>0.01</watertoemptyratio>
</data>